.travis.yml
LICENSE
MANIFEST.in
README.rst
pdftozpl
setup.py
src/zplgrf/__init__.py
src/zplgrf.egg-info/PKG-INFO
src/zplgrf.egg-info/SOURCES.txt
src/zplgrf.egg-info/dependency_links.txt
src/zplgrf.egg-info/requires.txt
src/zplgrf.egg-info/top_level.txt
src/zplgrf/tests/__init__.py
src/zplgrf/tests/input/asciihex-optimised-zb64.zpl
src/zplgrf/tests/input/image-optimised-zb64-copies2.zpl
src/zplgrf/tests/input/pdf-2pages-0.png
src/zplgrf/tests/input/pdf-2pages-1.png
src/zplgrf/tests/input/pdf-2pages.pdf
src/zplgrf/tests/input/pdf-asciihex.zpl
src/zplgrf/tests/input/pdf-image-centerofpixel.png
src/zplgrf/tests/input/pdf-image.png
src/zplgrf/tests/input/pdf-landscape.pdf
src/zplgrf/tests/input/pdf-landscape.png
src/zplgrf/tests/input/pdf-optimised-asciihex.zpl
src/zplgrf/tests/input/pdf-optimised-b64.zpl
src/zplgrf/tests/input/pdf-optimised-image.png
src/zplgrf/tests/input/pdf-optimised-zb64.zpl
src/zplgrf/tests/input/pdf.pdf