Metadata-Version: 1.1
Name: zplgrf
Version: 1.2
Summary: Tools to work with ZPL GRF images and CUPS
Home-page: https://github.com/kylemacfarlane/zplgrf
Author: Kyle MacFarlane
Author-email: kyle@deletethetrees.com
License: GPLv3
Platform: UNKNOWN
Classifier: Development Status :: 5 - Production/Stable
Classifier: License :: OSI Approved :: GNU General Public License v3 (GPLv3)
Classifier: Operating System :: OS Independent
Classifier: Programming Language :: Python :: 2.7
Classifier: Programming Language :: Python :: 3.3
Classifier: Programming Language :: Python :: 3.4
Classifier: Programming Language :: Python :: 3.5
